pysimstring/__init__.py
pysimstring/_simstring.so
pysimstring/simstring.py
pysimstring-1.3.0.dist-info/METADATA
pysimstring-1.3.0.dist-info/WHEEL
pysimstring-1.3.0.dist-info/top_level.txt
pysimstring-1.3.0.dist-info/RECORD
pysimstring-1.3.0.dist-info/licenses/LICENSE
