Metadata-Version: 2.4
Name: pysimstring
Version: 1.3.0
Summary: Easy to install clone of simstring
Home-page: https://github.com/percevalw/simstring
Author: Naoaki Okazaki & Blink Health & Luca Soldaini & Perceval Wajsbürt
Author-email: perceval.wajsburt@sorbonne-universite.fr
License-File: LICENSE
Dynamic: author
Dynamic: author-email
Dynamic: description
Dynamic: home-page
Dynamic: license-file
Dynamic: summary
